opentelemetry/instrumentation/sagemaker/__init__.py
opentelemetry/instrumentation/sagemaker/config.py
opentelemetry/instrumentation/sagemaker/event_emitter.py
opentelemetry/instrumentation/sagemaker/event_handler.py
opentelemetry/instrumentation/sagemaker/event_models.py
opentelemetry/instrumentation/sagemaker/reusable_streaming_body.py
opentelemetry/instrumentation/sagemaker/span_utils.py
opentelemetry/instrumentation/sagemaker/streaming_wrapper.py
opentelemetry/instrumentation/sagemaker/utils.py
opentelemetry/instrumentation/sagemaker/version.py
opentelemetry_instrumentation_sagemaker-0.51.1.dist-info/METADATA
opentelemetry_instrumentation_sagemaker-0.51.1.dist-info/WHEEL
opentelemetry_instrumentation_sagemaker-0.51.1.dist-info/entry_points.txt
opentelemetry_instrumentation_sagemaker-0.51.1.dist-info/RECORD
